{"nodes": [{"id": "users", "label": "users.py", "file_type": "code", "source_file": "backend/app/models/users.py", "source_location": "L1"}, {"id": "users_user", "label": "User", "file_type": "code", "source_file": "backend/app/models/users.py", "source_location": "L31"}, {"id": "basemodel", "label": "BaseModel", "file_type": "code", "source_file": "", "source_location": ""}, {"id": "users_user_repr", "label": ".__repr__()", "file_type": "code", "source_file": "backend/app/models/users.py", "source_location": "L48"}, {"id": "users_role", "label": "Role", "file_type": "code", "source_file": "backend/app/models/users.py", "source_location": "L52"}, {"id": "users_role_repr", "label": ".__repr__()", "file_type": "code", "source_file": "backend/app/models/users.py", "source_location": "L65"}, {"id": "users_permission", "label": "Permission", "file_type": "code", "source_file": "backend/app/models/users.py", "source_location": "L69"}, {"id": "users_permission_repr", "label": ".__repr__()", "file_type": "code", "source_file": "backend/app/models/users.py", "source_location": "L82"}], "edges": [{"source": "users", "target": "sqlalchemy", "relation": "imports_from", "confidence": "EXTRACTED", "source_file": "backend/app/models/users.py", "source_location": "L3", "weight": 1.0}, {"source": "users", "target": "sqlalchemy_orm", "relation": "imports_from", "confidence": "EXTRACTED", "source_file": "backend/app/models/users.py", "source_location": "L4", "weight": 1.0}, {"source": "users", "target": "base", "relation": "imports_from", "confidence": "EXTRACTED", "source_file": "backend/app/models/users.py", "source_location": "L5", "weight": 1.0}, {"source": "users", "target": "users_user", "relation": "contains", "confidence": "EXTRACTED", "source_file": "backend/app/models/users.py", "source_location": "L31", "weight": 1.0}, {"source": "users_user", "target": "basemodel", "relation": "inherits", "confidence": "EXTRACTED", "source_file": "backend/app/models/users.py", "source_location": "L31", "weight": 1.0}, {"source": "users_user", "target": "users_user_repr", "relation": "method", "confidence": "EXTRACTED", "source_file": "backend/app/models/users.py", "source_location": "L48", "weight": 1.0}, {"source": "users", "target": "users_role", "relation": "contains", "confidence": "EXTRACTED", "source_file": "backend/app/models/users.py", "source_location": "L52", "weight": 1.0}, {"source": "users_role", "target": "basemodel", "relation": "inherits", "confidence": "EXTRACTED", "source_file": "backend/app/models/users.py", "source_location": "L52", "weight": 1.0}, {"source": "users_role", "target": "users_role_repr", "relation": "method", "confidence": "EXTRACTED", "source_file": "backend/app/models/users.py", "source_location": "L65", "weight": 1.0}, {"source": "users", "target": "users_permission", "relation": "contains", "confidence": "EXTRACTED", "source_file": "backend/app/models/users.py", "source_location": "L69", "weight": 1.0}, {"source": "users_permission", "target": "basemodel", "relation": "inherits", "confidence": "EXTRACTED", "source_file": "backend/app/models/users.py", "source_location": "L69", "weight": 1.0}, {"source": "users_permission", "target": "users_permission_repr", "relation": "method", "confidence": "EXTRACTED", "source_file": "backend/app/models/users.py", "source_location": "L82", "weight": 1.0}]}