{"nodes": [{"id": "seed", "label": "seed.py", "file_type": "code", "source_file": "backend/scripts/seed.py", "source_location": "L1"}, {"id": "seed_get_or_create_permission", "label": "get_or_create_permission()", "file_type": "code", "source_file": "backend/scripts/seed.py", "source_location": "L72"}, {"id": "seed_seed", "label": "seed()", "file_type": "code", "source_file": "backend/scripts/seed.py", "source_location": "L87"}], "edges": [{"source": "seed", "target": "sys", "relation": "imports", "confidence": "EXTRACTED", "source_file": "backend/scripts/seed.py", "source_location": "L11", "weight": 1.0}, {"source": "seed", "target": "os", "relation": "imports", "confidence": "EXTRACTED", "source_file": "backend/scripts/seed.py", "source_location": "L12", "weight": 1.0}, {"source": "seed", "target": "argparse", "relation": "imports", "confidence": "EXTRACTED", "source_file": "backend/scripts/seed.py", "source_location": "L13", "weight": 1.0}, {"source": "seed", "target": "bcrypt", "relation": "imports", "confidence": "EXTRACTED", "source_file": "backend/scripts/seed.py", "source_location": "L14", "weight": 1.0}, {"source": "seed", "target": "dotenv", "relation": "imports_from", "confidence": "EXTRACTED", "source_file": "backend/scripts/seed.py", "source_location": "L21", "weight": 1.0}, {"source": "seed", "target": "sqlalchemy", "relation": "imports_from", "confidence": "EXTRACTED", "source_file": "backend/scripts/seed.py", "source_location": "L27", "weight": 1.0}, {"source": "seed", "target": "sqlalchemy_orm", "relation": "imports_from", "confidence": "EXTRACTED", "source_file": "backend/scripts/seed.py", "source_location": "L28", "weight": 1.0}, {"source": "seed", "target": "app_models_users", "relation": "imports_from", "confidence": "EXTRACTED", "source_file": "backend/scripts/seed.py", "source_location": "L31", "weight": 1.0}, {"source": "seed", "target": "seed_get_or_create_permission", "relation": "contains", "confidence": "EXTRACTED", "source_file": "backend/scripts/seed.py", "source_location": "L72", "weight": 1.0}, {"source": "seed", "target": "seed_seed", "relation": "contains", "confidence": "EXTRACTED", "source_file": "backend/scripts/seed.py", "source_location": "L87", "weight": 1.0}, {"source": "seed", "target": "traceback", "relation": "imports", "confidence": "EXTRACTED", "source_file": "backend/scripts/seed.py", "source_location": "L200", "weight": 1.0}, {"source": "seed_seed", "target": "seed_get_or_create_permission", "relation": "calls", "confidence": "INFERRED", "source_file": "backend/scripts/seed.py", "source_location": "L126", "weight": 0.8}]}